meetup_colab/__init__.py
meetup_colab/nvidia.py
meetup_colab-0.0.2.dist-info/METADATA
meetup_colab-0.0.2.dist-info/WHEEL
meetup_colab-0.0.2.dist-info/licenses/LICENSE
meetup_colab-0.0.2.dist-info/RECORD
